package_passgen/__init__.py
package_passgen/package_passgen.py
package_passgen/passgen.py
package_passgen-0.0.3.dist-info/LICENSE
package_passgen-0.0.3.dist-info/METADATA
package_passgen-0.0.3.dist-info/WHEEL
package_passgen-0.0.3.dist-info/top_level.txt
package_passgen-0.0.3.dist-info/RECORD
