Metadata-Version: 2.1
Name: package-passgen
Version: 0.0.3
Summary: A package to generate strong random passwords
Home-page: https://github.com/chris1109873/package_passgen
Author: Chris
Author-email: christopher.m9876@gmail.com
License: UNKNOWN
Platform: UNKNOWN
Classifier: Programming Language :: Python :: 3
Classifier: License :: OSI Approved :: MIT License
Classifier: Operating System :: OS Independent
Requires-Python: >=3.9
